lambda_labs_client/__init__.py
lambda_labs_client/cli.py
lambda_labs_client/client.py
lambda_labs_client-0.3.1.dist-info/licenses/LICENSE
lambda_labs_client-0.3.1.dist-info/METADATA
lambda_labs_client-0.3.1.dist-info/WHEEL
lambda_labs_client-0.3.1.dist-info/entry_points.txt
lambda_labs_client-0.3.1.dist-info/top_level.txt
lambda_labs_client-0.3.1.dist-info/RECORD
