Metadata-Version: 2.4
Name: lambda-labs-client
Version: 0.3.1
Summary: A Python client for Lambda Labs Cloud API for managing GPU instances
Author-email: Radek Osmulski <rosmulski@gmail.com>
License: MIT
Project-URL: Homepage, https://github.com/radekosmulski/lambda_labs_api
Project-URL: Bug Reports, https://github.com/radekosmulski/lambda_labs_api/issues
Project-URL: Source, https://github.com/radekosmulski/lambda_labs_api
Keywords: lambda,labs,gpu,cloud,api,machine-learning,ai
Classifier: Development Status :: 4 - Beta
Classifier: Intended Audience :: Developers
Classifier: License :: OSI Approved :: MIT License
Classifier: Operating System :: OS Independent
Classifier: Programming Language :: Python :: 3
Classifier: Programming Language :: Python :: 3.6
Classifier: Programming Language :: Python :: 3.7
Classifier: Programming Language :: Python :: 3.8
Classifier: Programming Language :: Python :: 3.9
Classifier: Programming Language :: Python :: 3.10
Classifier: Programming Language :: Python :: 3.11
Classifier: Programming Language :: Python :: 3.12
Classifier: Topic :: Software Development :: Libraries :: Python Modules
Classifier: Topic :: System :: Distributed Computing
Requires-Python: >=3.6
License-File: LICENSE
Requires-Dist: requests>=2.25.0
Requires-Dist: rich>=13.0.0
Requires-Dist: questionary>=2.0.0
Provides-Extra: dev
Requires-Dist: pytest>=6.0; extra == "dev"
Requires-Dist: pytest-cov; extra == "dev"
Requires-Dist: black; extra == "dev"
Requires-Dist: flake8; extra == "dev"
Requires-Dist: mypy; extra == "dev"
Dynamic: license-file
